{"cameraMode":{"drawMode":0,"name":"Shaded","section":"Shading Mode"},"sceneLighting":true,"audioPlay":false,"sceneViewState":{"showFog":true,"showMaterialUpdate":false,"showSkybox":true,"showFlares":true,"showImageEffects":true,"showParticleSystems":true},"in2DMode":false,"pivot":{"x":-1.124340295791626,"y":2.3029751777648927,"z":0.7192015051841736},"rotation":{"x":0.13493052124977113,"y":0.860666036605835,"z":-0.29710710048675539,"w":0.3908679485321045},"size":1.3552219867706299,"orthographic":false}