{"cameraMode":{"drawMode":0,"name":"Shaded","section":"Shading Mode"},"sceneLighting":true,"audioPlay":false,"sceneViewState":{"showFog":true,"showMaterialUpdate":false,"showSkybox":true,"showFlares":true,"showImageEffects":true,"showParticleSystems":true},"in2DMode":false,"pivot":{"x":0.14639654755592347,"y":-9.119924545288086,"z":0.8891830444335938},"rotation":{"x":0.47174790501594546,"y":-0.017192833125591279,"z":0.009200754575431347,"w":0.8815177083015442},"size":25.295408248901368,"orthographic":false}